{
    "0": {
        "Name": "Xyrabywefo",
        "TEL": "3805591977"
    },
    "1": {
        "Name": "Rogiruzoly",
        "TEL": "3805257735"
    },
    "2": {
        "Name": "Higuqyxazu",
        "TEL": "3806876578"
    },
    "3": {
        "Name": "Muhararuzi",
        "TEL": "3807811721"
    },
    "4": {
        "Name": "Maqahamaxa",
        "TEL": "3805049942"
    },
    "5": {
        "Name": "Ciloraqiha",
        "TEL": "3807425154"
    },
    "6": {
        "Name": "Lasyfebaji",
        "TEL": "3809077404"
    },
    "7": {
        "Name": "Caciricugi",
        "TEL": "3800224749"
    },
    "8": {
        "Name": "Cigexagysy",
        "TEL": "3809819621"
    },
    "9": {
        "Name": "Pubazozyqu",
        "TEL": "3803033734"
    },
    "10": {
        "Name": "Cagatumumy",
        "TEL": "3803695323"
    },
    "11": {
        "Name": "Tejizywify",
        "TEL": "3803698240"
    },
    "12": {
        "Name": "Tataqifiwa",
        "TEL": "3801898792"
    },
    "13": {
        "Name": "Rogagosute",
        "TEL": "3803912355"
    },
    "14": {
        "Name": "Qysihewaje",
        "TEL": "3804421934"
    },
    "15": {
        "Name": "Fygepabasi",
        "TEL": "3804166228"
    },
    "16": {
        "Name": "Cegytexeze",
        "TEL": "3809672871"
    },
    "17": {
        "Name": "Bisyfazuci",
        "TEL": "3808146415"
    },
    "18": {
        "Name": "Jotaherize",
        "TEL": "3803392198"
    },
    "19": {
        "Name": "Wezizeqese",
        "TEL": "3808758847"
    },
    "20": {
        "Name": "Xotyjybumi",
        "TEL": "3805355669"
    },
    "21": {
        "Name": "Lywysyziqu",
        "TEL": "3807791647"
    },
    "22": {
        "Name": "Fojoxyxemo",
        "TEL": "3806762574"
    },
    "23": {
        "Name": "Xylerojese",
        "TEL": "3801500349"
    },
    "24": {
        "Name": "Pesigesazu",
        "TEL": "3805731922"
    },
    "25": {
        "Name": "Tecyholawa",
        "TEL": "3804987300"
    },
    "26": {
        "Name": "Tasylyjosa",
        "TEL": "3808824881"
    },
    "27": {
        "Name": "Fybapihiwo",
        "TEL": "3808870805"
    },
    "28": {
        "Name": "Facetejuqi",
        "TEL": "3802316175"
    },
    "29": {
        "Name": "Qecuguxoto",
        "TEL": "3808173581"
    },
    "30": {
        "Name": "Byzeferatu",
        "TEL": "3809940532"
    },
    "31": {
        "Name": "Wohomopixa",
        "TEL": "3803116224"
    },
    "32": {
        "Name": "Wycuzuhigi",
        "TEL": "3801649898"
    },
    "33": {
        "Name": "Tisywemuro",
        "TEL": "3806773756"
    },
    "34": {
        "Name": "Tirofirogo",
        "TEL": "3802734300"
    },
    "35": {
        "Name": "Hypocymoha",
        "TEL": "3801663609"
    },
    "36": {
        "Name": "Wywusywigu",
        "TEL": "3806563892"
    },
    "37": {
        "Name": "Pywifeleba",
        "TEL": "3806836449"
    },
    "38": {
        "Name": "Xorawetuxi",
        "TEL": "3805373260"
    },
    "39": {
        "Name": "Xeqozuquge",
        "TEL": "3806163861"
    },
    "40": {
        "Name": "Hejelefaqy",
        "TEL": "3808267769"
    },
    "41": {
        "Name": "Sesezesexi",
        "TEL": "3808145250"
    },
    "42": {
        "Name": "Mixyzyqopa",
        "TEL": "3802580478"
    },
    "43": {
        "Name": "Wirufafiwa",
        "TEL": "3808033557"
    },
    "44": {
        "Name": "Jisaqogipo",
        "TEL": "3806389526"
    },
    "45": {
        "Name": "Zosoxiqifo",
        "TEL": "3809359128"
    },
    "46": {
        "Name": "Siraqucijy",
        "TEL": "3800849287"
    },
    "47": {
        "Name": "Larecapity",
        "TEL": "3806280340"
    },
    "48": {
        "Name": "Sawolowufe",
        "TEL": "3807229160"
    },
    "49": {
        "Name": "Hurexipory",
        "TEL": "3805827109"
    },
    "50": {
        "Name": "Qytifilora",
        "TEL": "3804784800"
    },
    "51": {
        "Name": "Fyjygaxype",
        "TEL": "3803537717"
    },
    "52": {
        "Name": "Jogojigama",
        "TEL": "3802615019"
    },
    "53": {
        "Name": "Miwimifaxo",
        "TEL": "3803967275"
    },
    "54": {
        "Name": "Wybifufuxe",
        "TEL": "3805420339"
    },
    "55": {
        "Name": "Sulytomepo",
        "TEL": "3802715409"
    },
    "56": {
        "Name": "Batytisify",
        "TEL": "3809561083"
    },
    "57": {
        "Name": "Gilojylexu",
        "TEL": "3802563833"
    },
    "58": {
        "Name": "Xetexoweqi",
        "TEL": "3808870210"
    },
    "59": {
        "Name": "Xyhysahyzi",
        "TEL": "3801785490"
    },
    "60": {
        "Name": "Gepejygabi",
        "TEL": "3809098228"
    },
    "61": {
        "Name": "Qufigeqaly",
        "TEL": "3803389078"
    },
    "62": {
        "Name": "Cyziqaroso",
        "TEL": "3808968747"
    },
    "63": {
        "Name": "Tacocuweju",
        "TEL": "3804763058"
    },
    "64": {
        "Name": "Qohixocyqu",
        "TEL": "3806034401"
    },
    "65": {
        "Name": "Zylywoxase",
        "TEL": "3807891015"
    },
    "66": {
        "Name": "Gycejutibi",
        "TEL": "3809376200"
    },
    "67": {
        "Name": "Jisiwypahe",
        "TEL": "3801786032"
    },
    "68": {
        "Name": "Zibotyluxo",
        "TEL": "3803773726"
    },
    "69": {
        "Name": "Zabaqywaco",
        "TEL": "3807651293"
    },
    "70": {
        "Name": "Gitawopyge",
        "TEL": "3804813940"
    },
    "71": {
        "Name": "Xehowazose",
        "TEL": "3800345169"
    },
    "72": {
        "Name": "Qoraqawybo",
        "TEL": "3800283376"
    },
    "73": {
        "Name": "Sipulycusu",
        "TEL": "3804224303"
    },
    "74": {
        "Name": "Pogaxuraqi",
        "TEL": "3808796676"
    },
    "75": {
        "Name": "Sagegejyqe",
        "TEL": "3805857619"
    },
    "76": {
        "Name": "Gowarubaxe",
        "TEL": "3801476446"
    },
    "77": {
        "Name": "Xecehyxizo",
        "TEL": "3804332638"
    },
    "78": {
        "Name": "Wociqyxibi",
        "TEL": "3807953576"
    },
    "79": {
        "Name": "Jeqomixaqy",
        "TEL": "3809062964"
    },
    "80": {
        "Name": "Cabyculuza",
        "TEL": "3807678425"
    },
    "81": {
        "Name": "Pirexefyze",
        "TEL": "3803359990"
    },
    "82": {
        "Name": "Wucicafizu",
        "TEL": "3801024745"
    },
    "83": {
        "Name": "Lygemazafo",
        "TEL": "3806570999"
    },
    "84": {
        "Name": "Lurahuwuma",
        "TEL": "3801676093"
    },
    "85": {
        "Name": "Xewytoboxa",
        "TEL": "3800029687"
    },
    "86": {
        "Name": "Zyjizocuco",
        "TEL": "3806878951"
    },
    "87": {
        "Name": "Tygugyxury",
        "TEL": "3809113022"
    },
    "88": {
        "Name": "Xowebapuxa",
        "TEL": "3801990173"
    },
    "89": {
        "Name": "Tacemuluso",
        "TEL": "3804042389"
    },
    "90": {
        "Name": "Mowalejuwu",
        "TEL": "3805837712"
    },
    "91": {
        "Name": "Jybysaqemy",
        "TEL": "3809980501"
    },
    "92": {
        "Name": "Wefocipale",
        "TEL": "3800030257"
    },
    "93": {
        "Name": "Xacuhujimo",
        "TEL": "3806251242"
    },
    "94": {
        "Name": "Fezehyjecu",
        "TEL": "3803622361"
    },
    "95": {
        "Name": "Cabacyhime",
        "TEL": "3807307340"
    },
    "96": {
        "Name": "Qegejufasy",
        "TEL": "3806234201"
    },
    "97": {
        "Name": "Bajyxejaxe",
        "TEL": "3807088413"
    },
    "98": {
        "Name": "Fuhujofofo",
        "TEL": "3808553744"
    },
    "99": {
        "Name": "Pelirazisu",
        "TEL": "3803463654"
    },
    "100": {
        "Name": "Mameqawaga",
        "TEL": "3807550658"
    },
    "101": {
        "Name": "Sugefobixy",
        "TEL": "3805039089"
    },
    "102": {
        "Name": "Bygytigobo",
        "TEL": "3802707166"
    },
    "103": {
        "Name": "Musymelari",
        "TEL": "3808809543"
    },
    "104": {
        "Name": "Rubujuriqe",
        "TEL": "3802626715"
    }
}